[
  {
    "id": 16,
    "image": "/img/main/6pm/01.webp",
    "sticker": "",
    "name": "[다노] 단백질 도시락 7종 세트_식단관리 고단백 냉동도시락",
    "composition": "1/2세트",
    "price": "31,500원",
    "sale_price": "",
    "top": [
      {
        "product_imgB": "/img/sub/prod016/big01.webp",
        "product_imgS": "/img/sub/prod016/small01.png",
        "header": "[다노] 단백질 도시락 7종 세트_식단관리 고단백 냉동도시락",
        "summary_info": "식단관리 입문자에게도 부담없는 도시락",
        "price": "31,500원",
        "sale_price": "",
        "discount": "",
        "composition": "1세트/2세트",
        "select": [
          {
            "option": "단백질 도시락(1세트)",
            "price": "31,500원",
            "sale_price": ""
          },
          {
            "option": "[-5%] 단백질 도시락(2세트)(+28,500원)",
            "price": "31,500원",
            "sale_price": ""
          }
        ]
      }
    ],
    "detail": [
      {
        "image_set": [
          { "image": "/img/sub/prod016/detail01.png" },
          { "image": "/img/sub/prod016/detail02.png" },
          { "image": "/img/sub/prod016/detail03.png" },
          { "image": "/img/sub/prod016/detail04.png" },
          { "image": "/img/sub/prod016/detail05.png" },
          { "image": "/img/sub/prod016/detail06.jpg" },
          { "image": "/img/sub/prod016/detail07.png" },
          { "image": "/img/sub/prod016/detail08.jpg" },
          { "image": "/img/sub/prod016/detail09.png" },
          { "image": "/img/sub/prod016/detail10.jpg" },
          { "image": "/img/sub/prod016/detail11.jpg" },
          { "image": "/img/sub/prod016/detail12.jpg" },
          { "image": "/img/sub/prod016/detail13.jpg" },
          { "image": "/img/sub/prod016/detail14.jpg" },
          { "image": "/img/sub/prod016/detail15.png" },
          { "image": "/img/sub/prod016/detail16.mp4" },
          { "image": "/img/sub/prod016/detail17.mp4" },
          { "image": "/img/sub/prod016/detail18.mp4" },
          { "image": "/img/sub/prod016/detail19.png" },
          { "image": "/img/sub/prod016/detail20.jpg" },
          { "image": "/img/sub/prod016/detail21.jpg" },
          { "image": "/img/sub/prod016/detail22.png" },
          { "image": "/img/sub/prod016/detail23.png" },
          { "image": "/img/sub/prod016/detail24.png" },
          { "image": "/img/sub/prod016/detail25.png" },
          { "image": "/img/sub/prod016/detail26.png" },
          { "image": "/img/sub/prod016/detail27.png" },
          { "image": "/img/sub/prod016/detail28.png" },
          { "image": "/img/sub/prod016/detail29.png" },
          { "image": "/img/sub/prod016/detail30.png" },
          { "image": "/img/sub/prod016/detail31.png" },
          { "image": "/img/sub/prod016/detail32.png" }
        ],
        "info_name": "단백질 도시락",
        "keep": "냉동보관",
        "volume": "상세페이지 참조"
      }
    ],
    "media_review": [
      { "media": "/img/sub/prod016/media01.jpg" },
      { "media": "/img/sub/prod016/media02.jpg" },
      { "media": "/img/sub/prod016/media03.jpg" },
      { "media": "/img/sub/prod016/media04.jpg" },
      { "media": "/img/sub/prod016/media05.jpg" },
      { "media": "/img/sub/prod016/media06.jpg" },
      { "media": "/img/sub/prod016/media07.jpg" },
      { "media": "/img/sub/prod016/media08.jpg" }
    ],
    "review": [
      {
        "tag_new": "",
        "tag_repurchase": "재구매",
        "date": "2023.10.26",
        "message": "항상 맛있게 먹고있어요!!",
        "user_name": "강",
        "option": "단백질 도시락(1세트)"
      },
      {
        "tag_new": "",
        "tag_repurchase": "",
        "date": "2023.10.22",
        "message": "단백질도시락이 한끼로 먹기 진짜 딱인듯! 많지도 적지도 않아요! ",
        "user_name": "박",
        "option": "단백질 도시락(1세트)"
      },
      {
        "tag_new": "",
        "tag_repurchase": "",
        "date": "2023.10.22",
        "message": "너무 알차고 맛있어요",
        "user_name": "오",
        "option": "단백질 도시락(1세트)"
      },
      {
        "tag_new": "",
        "tag_repurchase": "재구매",
        "date": "2023.10.19",
        "message": "한 끼 먹기 편해요",
        "user_name": "문",
        "option": "단백질 도시락(1세트)"
      },
      {
        "tag_new": "",
        "tag_repurchase": "",
        "date": "2023.10.15",
        "message": "너무맛있어요~ 저는 단백질보충을 위해 추가로 닭가슴살 더 얹어 먹었네요. 여러종류먹으니 질리지도 않고 또 주문할까합니다!!",
        "user_name": "박",
        "option": "단백질 도시락(1세트)"
      }
    ]
  },
  {
    "id": 17,
    "image": "/img/main/6pm/02.jpg",
    "sticker": "",
    "name": "[다노] 컬리플라워 도시락 6종 세트_식단관리 냉동도시락",
    "composition": "1/2세트",
    "price": "29,000원",
    "sale_price": "",
    "top": [
      {
        "product_imgB": "/img/sub/prod017/big01.jpg",
        "product_imgS": "/img/sub/prod017/small01.jpg",
        "header": "[다노] 컬리플라워 도시락 6종 세트_식단관리 냉동도시락",
        "summary_info": "과식한 다음날 가볍게 채우는",
        "price": "29,000원",
        "sale_price": "",
        "discount": "",
        "composition": "1/2세트",
        "select": [
          {
            "option": "컬리플라워 도시락 (1세트)",
            "price": "29,000원",
            "sale_price": ""
          },
          {
            "option": "[-6%] 컬리플라워 도시락 (2세트)(+25,520원)",
            "price": "29,000원",
            "sale_price": ""
          }
        ]
      }
    ],
    "detail": [
      {
        "image_set": [
          { "image": "/img/sub/prod017/detail01.png" },
          { "image": "/img/sub/prod017/detail02.png" },
          { "image": "/img/sub/prod017/detail03.mp4" },
          { "image": "/img/sub/prod017/detail04.png" },
          { "image": "/img/sub/prod017/detail05.jpg" },
          { "image": "/img/sub/prod017/detail06.jpg" },
          { "image": "/img/sub/prod017/detail07.jpg" },
          { "image": "/img/sub/prod017/detail08.jpg" },
          { "image": "/img/sub/prod017/detail09.png" }
        ],
        "info_name": "컬리플라워 도시락",
        "keep": "냉동보관",
        "volume": "상세페이지 참조"
      }
    ],
    "media_review": [
      { "media": "/img/sub/prod017/media01.jpg" },
      { "media": "/img/sub/prod017/media02.jpg" },
      { "media": "/img/sub/prod017/media03.jpg" },
      { "media": "/img/sub/prod017/media04.jpg" },
      { "media": "/img/sub/prod017/media05.jpg" },
      { "media": "/img/sub/prod017/media06.jpg" },
      { "media": "/img/sub/prod017/media07.jpg" },
      { "media": "/img/sub/prod017/media08.jpg" }
    ],
    "review": [
      {
        "tag_new": "NEW",
        "tag_repurchase": "",
        "date": "2023.10.27",
        "message": "맛있어요! 요즘 건강이 안좋아서 건강한 식단으로 먹고싶어서 샀는데 다 먹으면 또사려구요!",
        "user_name": "최",
        "option": "컬리플라워 도시락 (2세트)"
      },
      {
        "tag_new": "",
        "tag_repurchase": "재구매",
        "date": "2023.10.22",
        "message": "맛있어서 항상 시켜먹어요 감사합니다",
        "user_name": "박",
        "option": "컬리플라워 도시락 (1세트)"
      },
      {
        "tag_new": "",
        "tag_repurchase": "",
        "date": "2023.10.22",
        "message": "먹어본 냉동도시락중에는 맛이 제일 좋아서요",
        "user_name": "김",
        "option": "컬리플라워 도시락 (1세트)"
      },
      {
        "tag_new": "",
        "tag_repurchase": "재구매",
        "date": "2023.10.20",
        "message": "맛도 있고 다이어트도 되고 좋아요~",
        "user_name": "최",
        "option": "컬리플라워 도시락 (1세트)"
      },
      {
        "tag_new": "",
        "tag_repurchase": "",
        "date": "2023.10.14",
        "message": "다노샵 도시락이 맛있다고 소문은 들었는데, 다이어트 도시락은 다 거기서 거기 아닌가 하는 마음에 고민하다 이번에 구매해서 먹어봤어요 다른 도시락보다 맛있게 잘 먹었어요 ^^ 역시 소문은 괜히 나는게 아니네요 ㅎㅎ",
        "user_name": "김",
        "option": "컬리플라워 도시락 (1세트)"
      }
    ]
  },
  {
    "id": 18,
    "image": "/img/main/6pm/03.webp",
    "sticker": "",
    "name": "[다노] 닭가슴살도시락 7종 세트_식단관리 고단백 냉동도시락",
    "composition": "1/2세트",
    "price": "31,500원",
    "sale_price": "",
    "top": [
      {
        "product_imgB": "/img/sub/prod018/big01.webp",
        "product_imgS": "/img/sub/prod018/small01.png",
        "header": "[다노] 닭가슴살도시락 7종 세트_식단관리 고단백 냉동도시락",
        "summary_info": "7가지 닭가슴살 요리로 맛있게 즐기는 도시락",
        "price": "31,500원",
        "sale_price": "",
        "discount": "",
        "composition": "1/2세트",
        "select": [
          {
            "option": "닭가슴살 도시락(1세트)",
            "price": "31,500원",
            "sale_price": ""
          },
          {
            "option": "[-5%] 닭가슴살 도시락(2세트)(+28,500원)",
            "price": "31,500원",
            "sale_price": ""
          }
        ]
      }
    ],
    "detail": [
      {
        "image_set": [
          { "image": "/img/sub/prod018/detail01.png" },
          { "image": "/img/sub/prod018/detail02.mp4" },
          { "image": "/img/sub/prod018/detail03.png" },
          { "image": "/img/sub/prod018/detail04.png" },
          { "image": "/img/sub/prod018/detail05.png" },
          { "image": "/img/sub/prod018/detail06.jpg" },
          { "image": "/img/sub/prod018/detail07.jpg" },
          { "image": "/img/sub/prod018/detail08.jpg" },
          { "image": "/img/sub/prod018/detail09.png" },
          { "image": "/img/sub/prod018/detail10.png" },
          { "image": "/img/sub/prod018/detail11.png" },
          { "image": "/img/sub/prod018/detail12.png" },
          { "image": "/img/sub/prod018/detail13.png" },
          { "image": "/img/sub/prod018/detail14.png" },
          { "image": "/img/sub/prod018/detail15.png" },
          { "image": "/img/sub/prod018/detail16.png" },
          { "image": "/img/sub/prod018/detail17.png" },
          { "image": "/img/sub/prod018/detail18.png" },
          { "image": "/img/sub/prod018/detail19.png" },
          { "image": "/img/sub/prod018/detail20.png" }
        ],
        "info_name": "닭가슴살 도시락",
        "keep": "냉동보관",
        "volume": "상세페이지 참조"
      }
    ],
    "media_review": [
      { "media": "/img/sub/prod018/media01.jpg" },
      { "media": "/img/sub/prod018/media02.jpg" },
      { "media": "/img/sub/prod018/media03.jpg" },
      { "media": "/img/sub/prod018/media04.jpg" },
      { "media": "/img/sub/prod018/media05.jpg" },
      { "media": "/img/sub/prod018/media06.jpg" },
      { "media": "/img/sub/prod018/media07.jpg" },
      { "media": "/img/sub/prod018/media08.jpg" }
    ],
    "review": [
      {
        "tag_new": "",
        "tag_repurchase": "재구매",
        "date": "2023.10.26",
        "message": "재구매 강추입니다!!",
        "user_name": "강",
        "option": "닭가슴살 도시락(1세트)"
      },
      {
        "tag_new": "",
        "tag_repurchase": "",
        "date": "2023.10.23",
        "message": "허기지지않고 적당히 먹었다는 느낌이 들고 먹고난후 더부룩하지않고 가뿐해서 좋아요 맛도 저는 괜찮았습니다~~",
        "user_name": "임",
        "option": "닭가슴살 도시락(1세트)"
      },
      {
        "tag_new": "",
        "tag_repurchase": "재구매",
        "date": "2023.10.22",
        "message": "질릴줄 알았는데 닭가슴살이 맛있어서 한끼로 딱 좋아요",
        "user_name": "박",
        "option": "닭가슴살 도시락(1세트)"
      },
      {
        "tag_new": "",
        "tag_repurchase": "",
        "date": "2023.10.20",
        "message": "냉장고에 항상 쟁여놓는 도시락입니다",
        "user_name": "최",
        "option": "닭가슴살 도시락(1세트)"
      },
      {
        "tag_new": "",
        "tag_repurchase": "",
        "date": "2023.10.16",
        "message": "맛있어요!! 또구매하려고 들어왔어요",
        "user_name": "김",
        "option": "닭가슴살 도시락(1세트)"
      }
    ]
  },
  {
    "id": 19,
    "image": "/img/main/6pm/04.png",
    "sticker": "",
    "name": "[다노] 저당 곤약 도시락 7종 세트_식단관리 저당 냉동도시락",
    "composition": "1/2세트",
    "price": "33,000원",
    "sale_price": "",
    "top": [
      {
        "product_imgB": "/img/sub/prod019/big01.png",
        "product_imgS": "/img/sub/prod019/small01.png",
        "header": "[다노] 저당 곤약 도시락 7종 세트_식단관리 저당 냉동도시락",
        "summary_info": "탄수화물을 낮춘 도시락",
        "price": "33,000원",
        "sale_price": "",
        "discount": "",
        "composition": "1/2세트",
        "select": [
          {
            "option": "저당 곤약 도시락(1세트)",
            "price": "33,000원",
            "sale_price": ""
          },
          {
            "option": "[-5%] 저당 곤약 도시락(2세트)(+30,000원)",
            "price": "33,000원",
            "sale_price": ""
          }
        ]
      }
    ],
    "detail": [
      {
        "image_set": [
          { "image": "/img/sub/prod019/detail01.png" },
          { "image": "/img/sub/prod019/detail02.png" },
          { "image": "/img/sub/prod019/detail03.png" },
          { "image": "/img/sub/prod019/detail04.png" },
          { "image": "/img/sub/prod019/detail05.png" },
          { "image": "/img/sub/prod019/detail06.png" },
          { "image": "/img/sub/prod019/detail07.png" },
          { "image": "/img/sub/prod019/detail08.png" },
          { "image": "/img/sub/prod019/detail09.png" },
          { "image": "/img/sub/prod019/detail10.png" },
          { "image": "/img/sub/prod019/detail11.png" },
          { "image": "/img/sub/prod019/detail12.png" },
          { "image": "/img/sub/prod019/detail13.png" },
          { "image": "/img/sub/prod019/detail14.png" },
          { "image": "/img/sub/prod019/detail15.png" },
          { "image": "/img/sub/prod019/detail16.png" },
          { "image": "/img/sub/prod019/detail17.png" },
          { "image": "/img/sub/prod019/detail18.jpg" },
          { "image": "/img/sub/prod019/detail19.jpg" },
          { "image": "/img/sub/prod019/detail20.png" },
          { "image": "/img/sub/prod019/detail21.png" },
          { "image": "/img/sub/prod019/detail22.png" }
        ],
        "info_name": "저당 곤약 도시락",
        "keep": "냉동보관",
        "volume": "1개 200g"
      }
    ],
    "media_review": [
      { "media": "/img/sub/prod019/media01.jpg" },
      { "media": "/img/sub/prod019/media02.jpg" },
      { "media": "/img/sub/prod019/media03.jpg" },
      { "media": "/img/sub/prod019/media04.jpg" },
      { "media": "/img/sub/prod019/media05.jpg" },
      { "media": "/img/sub/prod019/media06.jpg" },
      { "media": "/img/sub/prod019/media07.jpg" },
      { "media": "/img/sub/prod019/media08.jpg" }
    ],
    "review": [
      {
        "tag_new": "NEW",
        "tag_repurchase": "재구매",
        "date": "2023.10.28",
        "message": "냉동실에 쟁여두고 먹어요",
        "user_name": "이",
        "option": " 저당 곤약 도시락(1세트)"
      },
      {
        "tag_new": "NEW",
        "tag_repurchase": "재구매",
        "date": "2023.10.28",
        "message": "다이어트 성공하고 있어요",
        "user_name": "이",
        "option": " 저당 곤약 도시락(1세트)"
      },
      {
        "tag_new": "",
        "tag_repurchase": "재구매",
        "date": "2023.10.27",
        "message": "다이어트 중인데 한끼 식사로 딱입니다.",
        "user_name": "",
        "option": " 저당 곤약 도시락(1세트)"
      },
      {
        "tag_new": "",
        "tag_repurchase": "재구매",
        "date": "2023.10.26",
        "message": "항살 맛있게 먹고있어요!!재구매 추천",
        "user_name": "강",
        "option": " 저당 곤약 도시락(1세트)"
      },
      {
        "tag_new": "",
        "tag_repurchase": "재구매",
        "date": "2023.10.24",
        "message": "매일 뭐먹지 고민안하고 그냥 손에 집히는거 돌려 먹어요~ 간편하고 좋습니당",
        "user_name": "이",
        "option": " 저당 곤약 도시락(1세트)"
      }
    ]
  }
]
